torch_fusion/__init__.py
torch_fusion/counting_model.py
torch_fusion/point_cloud_fusion.py
torch_fusion/util.py
torch_fusion/cuda/counting_model.cpp
torch_fusion/cuda/counting_model.cu
torch_fusion/cuda/point_cloud_fusion.cpp
torch_fusion/cuda/point_cloud_fusion.cu
grid_fusion_pytorch-0.1.2.dist-info/LICENSE
grid_fusion_pytorch-0.1.2.dist-info/METADATA
grid_fusion_pytorch-0.1.2.dist-info/WHEEL
grid_fusion_pytorch-0.1.2.dist-info/top_level.txt
grid_fusion_pytorch-0.1.2.dist-info/RECORD
