Metadata-Version: 2.1
Name: grid-fusion-pytorch
Version: 0.1.2
Summary: Efficient operations for fusing semantically annotated RGB-D measurements in a 3D voxel grid in pytorch.
Author-email: Jan Nogga <nogga@ais.uni-bonn.de>
License: GNU General Public License v3 (GPLv3)
Project-URL: Homepage, https://github.com/JanNogga/grid_fusion_pytorch
Project-URL: Bug Tracker, https://github.com/JanNogga/grid_fusion_pytorch/issues
Classifier: Programming Language :: Python :: 3
Classifier: License :: OSI Approved :: GNU General Public License v3 (GPLv3)
Classifier: Operating System :: OS Independent
Requires-Python: >=3.7
License-File: LICENSE
Requires-Dist: ninja
